MANIFEST.in
README.rst
setup.cfg
setup.py
pwdmeter/__init__.py
pwdmeter/i18n.py
pwdmeter/math.py
pwdmeter/meter.py
pwdmeter/utils.py
pwdmeter.egg-info/PKG-INFO
pwdmeter.egg-info/SOURCES.txt
pwdmeter.egg-info/dependency_links.txt
pwdmeter.egg-info/not-zip-safe
pwdmeter.egg-info/requires.txt
pwdmeter.egg-info/top_level.txt
pwdmeter/factors/__init__.py
pwdmeter/factors/casemix.py
pwdmeter/factors/charmix.py
pwdmeter/factors/factor.py
pwdmeter/factors/length.py
pwdmeter/factors/non_ascii.py
pwdmeter/factors/non_dictionary.py
pwdmeter/factors/variety.py
pwdmeter/i18n/cn.po
pwdmeter/i18n/en.po
pwdmeter/i18n/pwdmeter.pot
pwdmeter/i18n/cn/LC_MESSAGES/pwdmeter.mo
pwdmeter/i18n/en/LC_MESSAGES/pwdmeter.mo
pwdmeter/res/common.txt
tests/__init__.py
tests/test_casemix_factor.py
tests/test_charmix_factor.py
tests/test_length_factor.py
tests/test_math.py
tests/test_meter.py
tests/test_non_ascii_factory.py
tests/test_non_directionary_factory.py
tests/test_variety_factory.py